pkDemo/__init__.py
pkDemo-0.1.dist-info/METADATA
pkDemo-0.1.dist-info/WHEEL
pkDemo-0.1.dist-info/top_level.txt
pkDemo-0.1.dist-info/RECORD
