Metadata-Version: 2.1
Name: pkDemo
Version: 0.1
Summary: clinical trial information retriver
Home-page: https://github.com/xiaomujiang/setuptools_demo
Author: carpenter
Author-email: 962296332@qq.com
License: MIT
Platform: UNKNOWN
